acid_box/__init__.py
acid_box-0.0.0.dist-info/COPYING
acid_box-0.0.0.dist-info/METADATA
acid_box-0.0.0.dist-info/NOTICE
acid_box-0.0.0.dist-info/WHEEL
acid_box-0.0.0.dist-info/top_level.txt
acid_box-0.0.0.dist-info/RECORD
