Metadata-Version: 2.1
Name: acid-box
Version: 0.0.0
Summary: acid-box
Home-page: 
Author: Vincent Dary
Author-email: 
Classifier: Programming Language :: Python :: 3
Classifier: Operating System :: POSIX :: Linux
Classifier: License :: OSI Approved :: GNU General Public License v3 (GPLv3)
License-File: COPYING
License-File: NOTICE
